mopidy_local/__init__.py
mopidy_local/actor.py
mopidy_local/commands.py
mopidy_local/ext.conf
mopidy_local/library.py
mopidy_local/mtimes.py
mopidy_local/playback.py
mopidy_local/schema.py
mopidy_local/storage.py
mopidy_local/translator.py
mopidy_local/web.py
mopidy_local/sql/schema.sql
mopidy_local/sql/upgrade-v1.sql
mopidy_local/sql/upgrade-v2.sql
mopidy_local/sql/upgrade-v3.sql
mopidy_local/sql/upgrade-v4.sql
mopidy_local/sql/upgrade-v5.sql
mopidy_local/sql/upgrade-v6.sql
mopidy_local/www/index.html
Mopidy_Local-3.3.0.dist-info/LICENSE
Mopidy_Local-3.3.0.dist-info/METADATA
Mopidy_Local-3.3.0.dist-info/WHEEL
Mopidy_Local-3.3.0.dist-info/entry_points.txt
Mopidy_Local-3.3.0.dist-info/top_level.txt
Mopidy_Local-3.3.0.dist-info/RECORD
